{
    "enabled": false,
    "coin": "riecoin.json",

    "address": "RSoTqUcauJewHZYmPnM8w3p1LVcV5C2Fh1",

    "rewardRecipients": {
        "RF85xKkjgdSRm3NUfSTikpeJdis56kaRUn": 0
    },

    "paymentProcessing": {
        "enabled": false,
        "paymentInterval": 60,
        "minimumPayment": 1,
        "daemon": {
            "host": "127.0.0.1",
            "port": 28332,
            "user": "user",
            "password": "pass"
        }
    },

    "ports": {
        "3333": {
            "diff": 4
        }
    },

    "daemons": [
        {
            "host": "127.0.0.1",
            "port": 28332,
            "user": "user",
            "password": "pass"
        }
    ],

    "p2p": {
        "enabled": false,
        "host": "127.0.0.1",
        "port": 19333,
        "disableTransactions": true
    },

    "mposMode": {
        "enabled": false,
        "host": "127.0.0.1",
        "port": 3306,
        "user": "pool",
        "password": "incipio",
        "database": "mpos",
        "checkPassword": true,
        "autoCreateWorker": false
    }

}
